invisibleroads_macros_security/__init__.py
invisibleroads_macros_security-1.0.3.dist-info/METADATA
invisibleroads_macros_security-1.0.3.dist-info/WHEEL
invisibleroads_macros_security-1.0.3.dist-info/top_level.txt
invisibleroads_macros_security-1.0.3.dist-info/zip-safe
invisibleroads_macros_security-1.0.3.dist-info/RECORD
