Metadata-Version: 2.1
Name: invisibleroads-macros-security
Version: 1.0.3
Summary: Shortcut functions for security operations
Home-page: https://github.com/invisibleroads/invisibleroads-macros-security
Author: Roy Hyunjin Han
Author-email: rhh@crosscompute.com
Keywords: invisibleroads
Classifier: Programming Language :: Python
Classifier: License :: OSI Approved :: MIT License
Requires-Python: >=3.6
Provides-Extra: testing
Requires-Dist: pytest ; extra == 'testing'
Requires-Dist: pytest-cov ; extra == 'testing'
